RangeHTTPServer/__init__.py
RangeHTTPServer/__main__.py
rangehttpserver-1.3.3.dist-info/LICENSE
rangehttpserver-1.3.3.dist-info/METADATA
rangehttpserver-1.3.3.dist-info/WHEEL
rangehttpserver-1.3.3.dist-info/top_level.txt
rangehttpserver-1.3.3.dist-info/RECORD
