Metadata-Version: 2.1
Name: rangehttpserver
Version: 1.3.3
Summary: SimpleHTTPServer with support for Range requests
Home-page: https://github.com/danvk/RangeHTTPServer/
Author: Dan Vanderkam
Author-email: danvdk@gmail.com
Classifier: Environment :: Console
Classifier: Environment :: Web Environment
Classifier: Development Status :: 4 - Beta
Classifier: Intended Audience :: Developers
Classifier: License :: OSI Approved :: Apache Software License
License-File: LICENSE
